__init__.py
authentication.py
feed.py
geotab_lib-0.1.0.dist-info/METADATA
geotab_lib-0.1.0.dist-info/WHEEL
get.py
geotab_lib-0.1.0.dist-info/RECORD
